mitcl.py
mitcl-1.0.0.dist-info/LICENSE.txt
mitcl-1.0.0.dist-info/METADATA
mitcl-1.0.0.dist-info/RECORD
mitcl-1.0.0.dist-info/WHEEL
mitcl-1.0.0.dist-info/entry_points.txt
mitcl-1.0.0.dist-info/top_level.txt
