Metadata-Version: 2.1
Name: mitcl
Version: 1.0.0
Summary: A tool for MIT OCW check and download
Home-page: https://github.com/alipython/mitcl
Author: noxaean
Author-email: noxaean@gmail.com
License: MIT
Keywords: mit ocw check
Platform: UNKNOWN
Classifier: Development Status :: 3 - Alpha
Classifier: Topic :: Software Development :: Build Tools
Classifier: Programming Language :: Python :: 2
Classifier: Programming Language :: Python :: 2.7
Classifier: Programming Language :: Python :: 3
Classifier: Programming Language :: Python :: 3.2
Classifier: Programming Language :: Python :: 3.3
Classifier: Programming Language :: Python :: 3.4
